pyfedic/__init__.py
pyfedic/cells.py
pyfedic/dic.py
pyfedic/fem.py
pyfedic/fft.py
pyfedic/image.py
pyfedic/io.py
pyfedic/mesh/__init__.py
pyfedic/mesh/base_mesh.py
pyfedic/mesh/composite_mesh.py
pyfedic/mesh/image_mesh.py
pyfedic/mesh/regular_mesh.py
pyfedic/params.py
pyfedic/run_fedic.py
pyfedic/tictoc.py
pyfedic-25.11.0.dist-info/LICENSE.txt
pyfedic-25.11.0.dist-info/METADATA
pyfedic-25.11.0.dist-info/WHEEL
pyfedic-25.11.0.dist-info/entry_points.txt
pyfedic-25.11.0.dist-info/RECORD
