Metadata-Version: 2.3
Name: pyfedic
Version: 25.11.0
Summary: Digital Image (2D/3D) Correlation Software
License: CECILL-2.1
Author: Joël Lachambre
Author-email: joel.lachambre@cnrs.fr
Requires-Python: >=3.9,<3.13
Classifier: Intended Audience :: Developers
Classifier: Intended Audience :: Science/Research
Classifier: License :: OSI Approved :: CEA CNRS Inria Logiciel Libre License, version 2.1 (CeCILL-2.1)
Classifier: Operating System :: OS Independent
Classifier: Programming Language :: Python :: 3
Classifier: Programming Language :: Python :: 3.9
Classifier: Programming Language :: Python :: 3.10
Classifier: Programming Language :: Python :: 3.11
Classifier: Programming Language :: Python :: 3.12
Classifier: Topic :: Scientific/Engineering
Classifier: Topic :: Software Development :: Libraries :: Python Modules
Provides-Extra: all
Provides-Extra: cython
Provides-Extra: extra
Requires-Dist: imagecodecs (>=2024.1.30,<2025.0.0) ; extra == "extra" or extra == "all"
Requires-Dist: imageio (>=2.37.0,<3.0.0)
Requires-Dist: meshio (>=5.3.5,<6.0.0) ; extra == "extra" or extra == "all"
Requires-Dist: numpy (>2.0.0)
Requires-Dist: pyfedic_cython (>=25.9.2,<26.0.0) ; extra == "cython" or extra == "all"
Requires-Dist: rich (>=14.1.0,<15.0.0)
Requires-Dist: scipy (>1.11.0)
Requires-Dist: sympy (>=1.14.0,<2.0.0)
Requires-Dist: tifffile (>=2024.1.30,<2025.0.0) ; extra == "extra" or extra == "all"
Project-URL: Documentation, https://sourcesup.renater.fr/www/pyfedic/html
Project-URL: Homepage, https://sourcesup.renater.fr/www/pyfedic/
Project-URL: Repository, https://sourcesup.renater.fr/scm/?group_id=6036
